setup.py
pygkv/GitDatabase.py
pygkv/__init__.py
pygkv.egg-info/PKG-INFO
pygkv.egg-info/SOURCES.txt
pygkv.egg-info/dependency_links.txt
pygkv.egg-info/requires.txt
pygkv.egg-info/top_level.txt