Metadata-Version: 1.1
Name: pygkv
Version: 0.2
Summary: A library to use Git as Key-Value store
Home-page: https://github.com/ishankhare07/PyGKV
Author: Ishan Khare
Author-email: ishankhare07@gmail.com
License: MIT
Keywords: Git Data Persistence Databases Key-Value Store
Platform: UNKNOWN
Classifier: Development Status :: 4 - Beta
Classifier: Intended Audience :: Developers
Classifier: Topic :: Database
Classifier: License :: OSI Approved :: MIT License
Classifier: Programming Language :: Python :: 2.7
Classifier: Programming Language :: Python :: 3.4
